tbbackoff/__init__.py
tbbackoff-0.0.4.dist-info/METADATA
tbbackoff-0.0.4.dist-info/WHEEL
tbbackoff-0.0.4.dist-info/entry_points.txt
tbbackoff-0.0.4.dist-info/top_level.txt
tbbackoff-0.0.4.dist-info/RECORD
