Metadata-Version: 2.1
Name: tbbackoff
Version: 0.0.4
Summary: Implementacion de token bucket con backoff exponencial
Home-page: https://github.com/radiocutfm/tbbackoff
Author: Lambda Sistemas
Author-email: desarrollo@fierro.com.ar
License: MIT
Platform: UNKNOWN
Classifier: License :: OSI Approved :: MIT License
Classifier: Programming Language :: Python :: 2
Classifier: Programming Language :: Python :: 3
Classifier: Programming Language :: Python :: 3.7
